pytest-custom-timeout/src/pytest_custom_timeout/__init__.py
pytest-custom-timeout/src/pytest_custom_timeout/plugin.py
pytest-custom-timeout/src/pytest_custom_timeout/py.typed
pytest-custom-timeout/src/pytest_custom_timeout/version.py
pytest-custom-timeout/tests/conftest.py
pytest-custom-timeout/tests/test_failure_demo.py
pytest-custom-timeout/tests/test_pytest_custom_timeout.py
pytest_custom_timeout/__init__.py
pytest_custom_timeout/plugin.py
pytest_custom_timeout/py.typed
pytest_custom_timeout/version.py
pytest_custom_timeout-0.5.1.dist-info/LICENSE
pytest_custom_timeout-0.5.1.dist-info/METADATA
pytest_custom_timeout-0.5.1.dist-info/WHEEL
pytest_custom_timeout-0.5.1.dist-info/entry_points.txt
pytest_custom_timeout-0.5.1.dist-info/top_level.txt
pytest_custom_timeout-0.5.1.dist-info/RECORD
