Metadata-Version: 2.1
Name: pytest-custom-timeout
Version: 0.5.1
Summary: Use custom logic when a test times out. Based on pytest-timeout.
Author-email: Adam Nogowski <anogowski@live.com>
Maintainer-email: Adam Nogowski <anogowski@live.com>
License: 
Project-URL: Repository, https://github.com/anogowski/pytest-custom-timeout
Classifier: Framework :: Pytest
Classifier: Development Status :: 4 - Beta
Classifier: Environment :: Console
Classifier: Environment :: Plugins
Classifier: Intended Audience :: Developers
Classifier: Operating System :: POSIX
Classifier: Programming Language :: Python
Classifier: Programming Language :: Python :: 3.11
Classifier: Programming Language :: Python :: 3.12
Classifier: Programming Language :: Python :: 3 :: Only
Classifier: Programming Language :: Python :: Implementation :: CPython
Classifier: Programming Language :: Python :: Implementation :: PyPy
Classifier: License :: DFSG approved
Classifier: License :: OSI Approved :: MIT License
Classifier: License :: OSI Approved :: BSD License
Classifier: License :: OSI Approved :: Mozilla Public License 2.0 (MPL 2.0)
Classifier: Topic :: Software Development :: Quality Assurance
Classifier: Topic :: Software Development :: Testing
Classifier: Topic :: Utilities
Requires-Python: >=3.11
License-File: LICENSE
Requires-Dist: pytest>=8.0.0
